developers_chamber/__init__.py
developers_chamber/bitbucket_utils.py
developers_chamber/docker_utils.py
developers_chamber/ecs_utils.py
developers_chamber/git_utils.py
developers_chamber/gitlab_utils.py
developers_chamber/jira_utils.py
developers_chamber/project_utils.py
developers_chamber/slack_utils.py
developers_chamber/toggle_utils.py
developers_chamber/types.py
developers_chamber/utils.py
developers_chamber/version_utils.py
developers_chamber/bin/__init__.py
developers_chamber/bin/pydev.py
developers_chamber/click/__init__.py
developers_chamber/click/options.py
developers_chamber/qa/__init__.py
developers_chamber/qa/base.py
developers_chamber/qa/checks.py
developers_chamber/scripts/__init__.py
developers_chamber/scripts/bitbucket.py
developers_chamber/scripts/docker.py
developers_chamber/scripts/ecs.py
developers_chamber/scripts/git.py
developers_chamber/scripts/gitlab.py
developers_chamber/scripts/init_aliasses.py
developers_chamber/scripts/jira.py
developers_chamber/scripts/project.py
developers_chamber/scripts/qa.py
developers_chamber/scripts/sh.py
developers_chamber/scripts/slack.py
developers_chamber/scripts/toggle.py
developers_chamber/scripts/version.py
skip_developers_chamber-1.6.2.dist-info/licenses/LICENSE
skip_developers_chamber-1.6.2.dist-info/METADATA
skip_developers_chamber-1.6.2.dist-info/WHEEL
skip_developers_chamber-1.6.2.dist-info/entry_points.txt
skip_developers_chamber-1.6.2.dist-info/top_level.txt
skip_developers_chamber-1.6.2.dist-info/RECORD
