Metadata-Version: 2.4
Name: skip-developers-chamber
Version: 1.6.2
Summary: A small plugin which help with development, deployment, git
Home-page: https://github.com/skip-pay/developers-chamber
Author: Druids team
Author-email: matllubos@gmail.com
License: MIT
Keywords: django,skripts,easy live,git,bitbucket,Jira
License-File: LICENSE
Requires-Dist: boto3<2
Requires-Dist: click>=7.0
Requires-Dist: click-completion==0.5.2
Requires-Dist: coloredlogs==10.0
Requires-Dist: gitpython==3.1.30
Requires-Dist: isort>=5.12.0
Requires-Dist: jira==3.10.5
Requires-Dist: oauthlib==3.1.0
Requires-Dist: pip-tools==6.13.0
Requires-Dist: python-dotenv==0.14.0
Requires-Dist: python-hosts==0.4.6
Requires-Dist: requests>=2.23.0
Requires-Dist: slack-sdk==3.23.0
Requires-Dist: skip-TogglPy==0.2.0
Requires-Dist: unidecode==1.1.1
Dynamic: author
Dynamic: author-email
Dynamic: home-page
Dynamic: keywords
Dynamic: license
Dynamic: license-file
Dynamic: requires-dist
Dynamic: summary
